_kohlrahbi_version.py
kohlrahbi/__init__.py
kohlrahbi/docxfilefinder.py
kohlrahbi/logger.ini
kohlrahbi/logger.py
kohlrahbi/py.typed
kohlrahbi/read_functions.py
kohlrahbi/row_type_checker.py
kohlrahbi/seed.py
kohlrahbi/table_header.py
kohlrahbi/version.py
kohlrahbi/ahb/__init__.py
kohlrahbi/ahb/command.py
kohlrahbi/ahbtable/__init__.py
kohlrahbi/ahbtable/ahbcondtions.py
kohlrahbi/ahbtable/ahbpackagetable.py
kohlrahbi/ahbtable/ahbsubtable.py
kohlrahbi/ahbtable/ahbtable.py
kohlrahbi/ahbtable/ahbtablerow.py
kohlrahbi/changehistory/__init__.py
kohlrahbi/changehistory/changehistorytable.py
kohlrahbi/changehistory/command.py
kohlrahbi/conditions/__init__.py
kohlrahbi/conditions/allgemeine_festlegungen.py
kohlrahbi/conditions/command.py
kohlrahbi/docxtablecells/__init__.py
kohlrahbi/docxtablecells/bedinungscell.py
kohlrahbi/docxtablecells/bodycell.py
kohlrahbi/docxtablecells/edifactstrukturcell.py
kohlrahbi/enums/__init__.py
kohlrahbi/enums/ahbexportfileformat.py
kohlrahbi/enums/flat_ahb_row_type.py
kohlrahbi/enums/row_type.py
kohlrahbi/enums/row_type_color.py
kohlrahbi/format_versions/FV2104_all_known_pruefis.toml
kohlrahbi/format_versions/FV2110_all_known_pruefis.toml
kohlrahbi/format_versions/FV2210_all_known_pruefis.toml
kohlrahbi/format_versions/FV2304_all_known_pruefis.toml
kohlrahbi/format_versions/FV2310_all_known_pruefis.toml
kohlrahbi/format_versions/FV2404_all_known_pruefis.toml
kohlrahbi/format_versions/FV2410_all_known_pruefis.toml
kohlrahbi/models/__init__.py
kohlrahbi/models/anwendungshandbuch.py
kohlrahbi/models/edifact_components.py
kohlrahbi/models/flat_ahb_reader.py
kohlrahbi/models/sqlmodels/__init__.py
kohlrahbi/models/sqlmodels/anwendungshandbuch.py
kohlrahbi/qualitymap/__init__.py
kohlrahbi/qualitymap/command.py
kohlrahbi/qualitymap/qualitymaptable.py
kohlrahbi/unfoldedahb/__init__.py
kohlrahbi/unfoldedahb/unfoldedahbline.py
kohlrahbi/unfoldedahb/unfoldedahbtable.py
kohlrahbi/unfoldedahb/unfoldedahbtablemetadata.py
kohlrahbi-1.13.0.dist-info/METADATA
kohlrahbi-1.13.0.dist-info/WHEEL
kohlrahbi-1.13.0.dist-info/entry_points.txt
kohlrahbi-1.13.0.dist-info/licenses/LICENSE
kohlrahbi-1.13.0.dist-info/RECORD
