Metadata-Version: 2.4
Name: kohlrahbi
Version: 1.13.0
Summary: Tool to generate machine readable files from AHB documents
Project-URL: Changelog, https://github.com/Hochfrequenz/kohlrahbi/releases
Project-URL: Homepage, https://github.com/Hochfrequenz/kohlrahbi
Author-email: Kevin Krechan <kevin.krechan@hochfrequenz.de>
License: GPL
License-File: LICENSE
Keywords: ahb,automation,bdew,edi@energy
Classifier: Development Status :: 4 - Beta
Classifier: Environment :: Console
Classifier: Intended Audience :: Developers
Classifier: License :: OSI Approved :: GNU General Public License v3 (GPLv3)
Classifier: Operating System :: OS Independent
Classifier: Programming Language :: Python
Classifier: Programming Language :: Python :: 3 :: Only
Classifier: Programming Language :: Python :: 3.11
Classifier: Programming Language :: Python :: 3.12
Classifier: Programming Language :: Python :: 3.13
Requires-Python: >=3.11
Requires-Dist: click>=8.1.7
Requires-Dist: colorlog>=6.9.0
Requires-Dist: edi-energy-scraper>=2.0.0
Requires-Dist: efoli>=1.4.0
Requires-Dist: more-itertools>=10.5.0
Requires-Dist: openpyxl>=3.1.5
Requires-Dist: pandas>=2.2.3
Requires-Dist: pydantic>=2.9.2
Requires-Dist: python-docx>=1.1.2
Requires-Dist: pytz>=2024.2
Requires-Dist: tomlkit>=0.13.2
Requires-Dist: xlsxwriter>=3.2.0
Provides-Extra: coverage
Requires-Dist: coverage==7.6.10; extra == 'coverage'
Provides-Extra: dev
Requires-Dist: black==25.1.0; extra == 'dev'
Requires-Dist: coverage==7.6.10; extra == 'dev'
Requires-Dist: dictdiffer==0.9.0; extra == 'dev'
Requires-Dist: freezegun==1.5.1; extra == 'dev'
Requires-Dist: isort==5.13.2; extra == 'dev'
Requires-Dist: mypy==1.11.2; extra == 'dev'
Requires-Dist: networkx-stubs==0.0.1; extra == 'dev'
Requires-Dist: pandas-stubs==2.2.3.241126; extra == 'dev'
Requires-Dist: pylint-pydantic==0.3.5; extra == 'dev'
Requires-Dist: pylint==3.3.3; extra == 'dev'
Requires-Dist: pytest-datafiles==3.0.0; extra == 'dev'
Requires-Dist: pytest==8.3.4; extra == 'dev'
Requires-Dist: sqlalchemy[mypy]>=2.0.37; extra == 'dev'
Requires-Dist: sqlmodel>=0.0.22; extra == 'dev'
Requires-Dist: syrupy==4.8.1; extra == 'dev'
Requires-Dist: types-freezegun==1.1.10; extra == 'dev'
Requires-Dist: types-requests==2.32.0.20241016; extra == 'dev'
Provides-Extra: formatting
Requires-Dist: black==25.1.0; extra == 'formatting'
Requires-Dist: isort==5.13.2; extra == 'formatting'
Provides-Extra: lint
Requires-Dist: pylint-pydantic==0.3.5; extra == 'lint'
Requires-Dist: pylint==3.3.3; extra == 'lint'
Provides-Extra: spell-check
Requires-Dist: codespell==2.4.0; extra == 'spell-check'
Provides-Extra: sqlmodels
Requires-Dist: sqlalchemy[mypy]>=2.0.37; extra == 'sqlmodels'
Requires-Dist: sqlmodel>=0.0.22; extra == 'sqlmodels'
Provides-Extra: test
Requires-Dist: coverage==7.6.10; extra == 'test'
Requires-Dist: dictdiffer==0.9.0; extra == 'test'
Requires-Dist: freezegun==1.5.1; extra == 'test'
Requires-Dist: pytest-datafiles==3.0.0; extra == 'test'
Requires-Dist: pytest==8.3.4; extra == 'test'
Requires-Dist: sqlalchemy[mypy]>=2.0.37; extra == 'test'
Requires-Dist: sqlmodel>=0.0.22; extra == 'test'
Requires-Dist: syrupy==4.8.1; extra == 'test'
Provides-Extra: test-packaging
Requires-Dist: build==1.2.2.post1; extra == 'test-packaging'
Requires-Dist: twine==6.1.0; extra == 'test-packaging'
Provides-Extra: typecheck
Requires-Dist: mypy==1.11.2; extra == 'typecheck'
Requires-Dist: networkx-stubs==0.0.1; extra == 'typecheck'
Requires-Dist: pandas-stubs==2.2.3.241126; extra == 'typecheck'
Requires-Dist: pytest==8.3.4; extra == 'typecheck'
Requires-Dist: sqlalchemy[mypy]>=2.0.37; extra == 'typecheck'
Requires-Dist: sqlmodel>=0.0.22; extra == 'typecheck'
Requires-Dist: types-freezegun==1.1.10; extra == 'typecheck'
Requires-Dist: types-requests==2.32.0.20241016; extra == 'typecheck'
